{
  "folder": "Oaf4JXgHYgudsSrK",
  "name": "Scrabbler Skittermander",
  "type": "heritage",
  "effects": [],
  "system": {
    "_migration": {
      "version": 0.94,
      "previous": null
    },
    "description": {
      "value": "<p>You never mastered coordinating all six of your arms for manual manipulation, instead using the lowest two limbs for the extra mobility, balance, and stabilization of a natural climber. You have four arms (rather than six) and four legs (rather than two). You gain a climb Speed equal to your base land Speed and can climb using your feet, leaving your four arms free.</p>",
      "gm": ""
    },
    "publication": {
      "title": "Starfinder Player Core",
      "authors": "",
      "license": "ORC",
      "remaster": true
    },
    "rules": [
      {
        "key": "BaseSpeed",
        "selector": "climb",
        "value": "@actor.attributes.speed.value"
      }
    ],
    "slug": "scrabbler-skittermander",
    "traits": {
      "otherTags": [],
      "value": [],
      "rarity": "common"
    },
    "ancestry": {
      "name": "Skittermander",
      "slug": "skittermander",
      "uuid": "Compendium.sf2e-anachronism.ancestries.Item.0qcXAQo7iZkZXNO9"
    }
  },
  "img": "systems/pf2e/icons/default-icons/heritage.svg",
  "sort": 0,
  "ownership": {
    "default": 0,
    "cWwLchXkibIUDc9I": 3
  },
  "flags": {},
  "_stats": {
    "compendiumSource": null,
    "duplicateSource": null,
    "exportSource": null,
    "coreVersion": "13.346",
    "systemId": "pf2e",
    "systemVersion": "7.2.3"
  },
  "_id": "m9Nb3UrUoEGAxaCr",
  "_key": "!items!m9Nb3UrUoEGAxaCr"
}
