{
  "folder": "XRYlvHgabwIfyMq7",
  "name": "Tempering",
  "type": "heritage",
  "effects": [],
  "system": {
    "_migration": {
      "version": 0.94,
      "previous": null
    },
    "description": {
      "value": "<p>You're undergoing your Tempering, a coming-of-age ritual during which a kasatha rejects the formal traditions of their family and experiences other customs and traditions. You might be one of the Untempered, a kasatha who chooses to continue their Tempering beyond the traditional period. You become trained in Society and gain the @UUID[Compendium.pf2e.feats-srd.Item.X2jGFfLU5qI5XVot]{Streetwise} feat.</p>",
      "gm": ""
    },
    "publication": {
      "title": "Starfinder Player Core",
      "authors": "",
      "license": "ORC",
      "remaster": true
    },
    "rules": [
      {
        "key": "GrantItem",
        "uuid": "Compendium.pf2e.feats-srd.Item.X2jGFfLU5qI5XVot"
      },
      {
        "key": "ActiveEffectLike",
        "mode": "upgrade",
        "path": "system.skills.society.rank",
        "value": 1
      }
    ],
    "slug": "tempering",
    "traits": {
      "otherTags": [],
      "value": [],
      "rarity": "common"
    },
    "ancestry": {
      "name": "Kasatha",
      "slug": "kasatha",
      "uuid": "Compendium.sf2e-anachronism.ancestries.Item.H6dkr1GtoQhuQqJm"
    }
  },
  "img": "systems/pf2e/icons/default-icons/heritage.svg",
  "sort": 0,
  "ownership": {
    "default": 0,
    "cWwLchXkibIUDc9I": 3
  },
  "flags": {},
  "_stats": {
    "compendiumSource": null,
    "duplicateSource": null,
    "exportSource": null,
    "coreVersion": "13.346",
    "systemId": "pf2e",
    "systemVersion": "7.2.3"
  },
  "_id": "mLgNG46EWZuabvqA",
  "_key": "!items!mLgNG46EWZuabvqA"
}
