{
  "type": "feat",
  "name": "Crowd Control",
  "folder": "HGxuzcVt8hJHZRnX",
  "img": "modules/sf2e-anachronism/art/icons/feat.webp",
  "system": {
    "level": {
      "value": 2
    },
    "category": "skill",
    "traits": {
      "value": [
        "general",
        "skill"
      ],
      "rarity": "common",
      "otherTags": []
    },
    "publication": {
      "license": "ORC",
      "remaster": true,
      "title": "Starfinder Player Core",
      "authors": ""
    },
    "description": {
      "value": "<p>Your voice can be heard over the noise in a crowd. You gain a +2 circumstance bonus to Diplomacy checks against crowds. The first time each round you Stride into a square containing a crowd, you can attempt a @Check[diplomacy|dc:20] check to move the crowd out of your way. A GM might use a different DC under certain circumstances, such as when the crowd has a level or set DC to disperse.</p><hr /><p><strong>Critical Success</strong> As success, and the crowd departs from all adjacent squares as you move.</p><p><strong>Success</strong> The crowd disperses from squares you move into.</p><p><strong>Failure</strong> The crowd doesn't move, but you can continue moving.</p><p><strong>Critical Failure</strong> The crowd forcefully resists you and disrupts your Stride.</p>",
      "gm": ""
    },
    "rules": [
      {
        "key": "FlatModifier",
        "selector": "diplomacy",
        "value": 2,
        "predicate": [
          "crowd-control"
        ],
        "type": "circumstance"
      }
    ],
    "slug": "crowd-control",
    "_migration": {
      "version": 0.94,
      "previous": {
        "schema": null,
        "foundry": "13.346",
        "system": "7.2.2"
      }
    },
    "onlyLevel1": false,
    "maxTakable": 1,
    "actionType": {
      "value": "passive"
    },
    "actions": {
      "value": null
    },
    "prerequisites": {
      "value": [
        {
          "value": "expert in Diplomacy"
        }
      ]
    },
    "subfeatures": {
      "proficiencies": {},
      "senses": {},
      "suppressedFeatures": []
    },
    "location": null
  },
  "_id": "JFPGW8OiYNYtOYOL",
  "effects": [],
  "sort": 0,
  "ownership": {
    "default": 0,
    "cWwLchXkibIUDc9I": 3
  },
  "flags": {},
  "_stats": {
    "compendiumSource": null,
    "duplicateSource": null,
    "exportSource": null,
    "coreVersion": "13.346",
    "systemId": "pf2e",
    "systemVersion": "7.2.3"
  },
  "_key": "!items!JFPGW8OiYNYtOYOL"
}
