{
  "type": "equipment",
  "name": "Hideaway Limb (Commercial)",
  "folder": "RTmfkP0RlWpOTPHx",
  "system": {
    "description": {
      "gm": "",
      "value": "<p>You can conceal items inside a hidden compartment in one of your limbs (such as an arm, leg, or tail) and protect them with a passcode. The compartment holds items of negligible Bulk and items of light Bulk that are small enough to fit in your limb or can otherwise be folded or contracted to fit. A hideaway in a leg (in a human) can typically hold more than one in an arm, and your size also adjusts the capacity at the GM's discretion.</p><p>When the compartment is closed, the seam in your limb is difficult to detect. You gain a +1 item bonus to Stealth checks to Conceal an Object in a hideaway limb. Though this compartment can foil a cursory pat down, many security checkpoints include a scan to detect such devices.</p><p><strong>Activate—Draw</strong> <span class=\"pf2-icon\">1</span> (manipulate)</p><hr /><p><strong>Effect</strong> You Interact to draw an item @UUID[Compendium.pf2e.conditionitems.Item.DmAIPqOBomZ7H95W]{Concealed} in your hideaway limb.</p>"
    },
    "rules": [],
    "slug": "hideaway-limb-commercial",
    "_migration": {
      "version": 0.94,
      "lastMigration": null,
      "previous": {
        "schema": null,
        "foundry": "13.346",
        "system": "7.2.3"
      }
    },
    "traits": {
      "otherTags": [],
      "value": [
        "tech"
      ],
      "rarity": "common"
    },
    "publication": {
      "title": "Starfinder Player Core",
      "authors": "",
      "license": "ORC",
      "remaster": true
    },
    "level": {
      "value": 1
    },
    "quantity": 1,
    "baseItem": null,
    "bulk": {
      "value": 0.1
    },
    "hp": {
      "value": 0,
      "max": 0
    },
    "hardness": 0,
    "price": {
      "value": {
        "sp": 140
      }
    },
    "equipped": {
      "carryType": "worn",
      "invested": null
    },
    "containerId": null,
    "size": "med",
    "material": {
      "type": null,
      "grade": null
    },
    "identification": {
      "status": "identified",
      "unidentified": {
        "name": "Unusual Object",
        "img": "systems/pf2e/icons/unidentified_item_icons/adventuring_gear.webp",
        "data": {
          "description": {
            "value": ""
          }
        }
      },
      "misidentified": {}
    },
    "usage": {
      "value": "implanted"
    },
    "subitems": []
  },
  "_id": "xTbGz4uDeCWwMyVA",
  "img": "modules/sf2e-anachronism/art/icons/equipment/other/blue-glove.webp",
  "effects": [],
  "sort": 101563,
  "ownership": {
    "default": 0,
    "yECpvB6rPSLHk9Lh": 3
  },
  "flags": {},
  "_stats": {
    "compendiumSource": null,
    "duplicateSource": null,
    "exportSource": null,
    "coreVersion": "13.346",
    "systemId": "pf2e",
    "systemVersion": "7.2.3"
  },
  "_key": "!items!xTbGz4uDeCWwMyVA"
}
